Scarlet/__init__.py
Scarlet/booleanSubsetCover.py
Scarlet/convert2dfa.py
Scarlet/directed_ltl.py
Scarlet/formulaTree.py
Scarlet/genBenchmarks.py
Scarlet/inferLTL.py
Scarlet/ltllearner.py
Scarlet/sample.py
Scarlet_ltl-0.0.4.dist-info/METADATA
Scarlet_ltl-0.0.4.dist-info/WHEEL
Scarlet_ltl-0.0.4.dist-info/top_level.txt
Scarlet_ltl-0.0.4.dist-info/RECORD
