Metadata-Version: 2.1
Name: Scarlet-ltl
Version: 0.0.4
Summary: A package for learning LTL formulas from a sample consisting of traces partitioned into positive and negative
Author-email: Ritam Raha <ritam.raha18@gmail.com>, Rajarshi Roy <rajarshi008@gmail.com>, Nathanael Fijalkow <nathanael.fijalkow@gmail.com>, Daniel Neider <daniel.neider@uni-oldenburg.de>
License: Copyright (c) 2022 University of Antwerp, Belgium & LaBRI, University of Bordeaux, France
Project-URL: Homepage, https://github.com/rajarshi008/Scarlet
Project-URL: Paper, https://link.springer.com/chapter/10.1007/978-3-030-99524-9_14
Classifier: Programming Language :: Python :: 3
Classifier: License :: OSI Approved :: MIT License
Classifier: Operating System :: OS Independent
Requires-Python: >=3.7
Requires-Dist: lark
Requires-Dist: graphviz
Requires-Dist: ltlf2dfa
